README.md
setup.py
nutsh/__init__.py
nutsh/track.py
nutsh/track.pyi
nutsh/track_grpc.py
nutsh.egg-info/PKG-INFO
nutsh.egg-info/SOURCES.txt
nutsh.egg-info/dependency_links.txt
nutsh.egg-info/requires.txt
nutsh.egg-info/top_level.txt
nutsh/lib/__init__.py
nutsh/lib/image.py
nutsh/lib/logging.py
nutsh/proto/__init__.py
nutsh/proto/schema/__init__.py
nutsh/proto/schema/v1/__init__.py
nutsh/proto/schema/v1/common_pb2.py
nutsh/proto/schema/v1/common_pb2.pyi
nutsh/proto/schema/v1/common_pb2_grpc.py
nutsh/proto/schema/v1/train_pb2.py
nutsh/proto/schema/v1/train_pb2.pyi
nutsh/proto/schema/v1/train_pb2_grpc.py
nutsh/proto/service/__init__.py
nutsh/proto/service/v1/__init__.py
nutsh/proto/service/v1/segmentation_pb2.py
nutsh/proto/service/v1/segmentation_pb2.pyi
nutsh/proto/service/v1/segmentation_pb2_grpc.py
nutsh/proto/service/v1/track_pb2.py
nutsh/proto/service/v1/track_pb2.pyi
nutsh/proto/service/v1/track_pb2_grpc.py